[
  {
    "Date": "000000001970-01-05-0000January 5, 1970",
    "Location": "Washington, D.C. !Washington, D.C.",
    "Deaths": "0,000,0011",
    "Injuries": "0,000,0011",
    "Description": "15-year-old Tyrone Perry, was killed at Hine Junior High School. In a separate incident another student at a different school was wounded.[149]",
    "coords": {
      "lat": 38.9071923,
      "lon": -77.0368707
    }
  },
  {
    "Date": "000000001970-02-11-0000February 11, 1970",
    "Location": "Philadelphia, Pennsylvania !Philadelphia, Pennsylvania",
    "Deaths": "0,000,0011",
    "Injuries": "0,000,0012",
    "Description": "University of Pennsylvania professors, 40-year-old Walter Koppelman, and 45-year-old Oscar Goldman, were shot by 33-year-old disgruntled graduate student, Robert Cantor, during a seminar. Cantor then took his own life. Koppelman died March 5 from his injuries, but Goldman recovered.[150]",
    "coords": {
      "lat": 39.9525839,
      "lon": -75.1652215
    }
  },
  {
    "Date": "000000001970-05-04-0000May 4, 1970",
    "Location": "Kent, Ohio !Kent, Ohio",
    "Deaths": "0,000,0014",
    "Injuries": "0,000,0019",
    "Description": "Kent State shootings: During protests of the Vietnam War at Kent State University, armed National Guard Soldiers opened fire on unarmed students, killing four people.[136][151][152]",
    "coords": {
      "lat": 41.1536674,
      "lon": -81.3578859
    }
  },
  {
    "Date": "000000001970-05-15-0000May 15, 1970",
    "Location": "Jackson, Mississippi !Jackson, Mississippi",
    "Deaths": "0,000,0012",
    "Injuries": "0,000,00112",
    "Description": "Jackson State killings: Two students were killed and twelve others injured when police opened fire on students gathered to protest the US military presence in Cambodia.[153][154][155]",
    "coords": {
      "lat": 32.2987573,
      "lon": -90.1848103
    }
  },
  {
    "Date": "000000001970-11-20-0000November 20, 1970",
    "Location": "Chicago, Illinois !Chicago, Illinois",
    "Deaths": "0,000,0010",
    "Injuries": "0,000,0012",
    "Description": "Two students were shot while standing in a second floor hallway of Harlan High School. 15-year-old Kenneth House, was shot in the lower left abdomen, his condition was described as serious. 14-year-old Portia Walls, suffered a superficial wound on her lower back. The incident was thought to have involved gang recruiting in the school.[156]",
    "coords": {
      "lat": 41.8781136,
      "lon": -87.6297982
    }
  },
  {
    "Date": "000000001971-02-02-0000February 2, 1971",
    "Location": "Philadelphia, Pennsylvania !Philadelphia, Pennsylvania",
    "Deaths": "0,000,0011",
    "Injuries": "0,000,0010",
    "Description": "56-year-old teacher, Samson L. Freedman, was killed as he left Morris E. Leeds School, by 14-year-old student, Kevin Simmons. Freedman had suspended Simmons earlier in the day for cursing in the hallway.[157]",
    "coords": {
      "lat": 39.9525839,
      "lon": -75.1652215
    }
  },
  {
    "Date": "000000001971-11-11-0000November 11, 1971",
    "Location": "Spokane, Washington !Spokane, Washington",
    "Deaths": "0,000,0012",
    "Injuries": "0,000,0014",
    "Description": "21-year-old former MIT student, Larry J. Harmon, armed with a rifle, killed 68-year-old caretaker, Hilary Kunzon, who came upon him wrecking St. Aloysius Roman Catholic Church, then fled onto the campus of Gonzaga University, where he wounded four more people before police officers killed him. Harmon was described by his father as a religious fanatic claiming to have visions.[158]",
    "coords": {
      "lat": 47.6587802,
      "lon": -117.4260465
    }
  },
  {
    "Date": "000000001973-02-26-0000February 26, 1973",
    "Location": "Richmond, Virginia !Richmond, Virginia",
    "Deaths": "0,000,0011",
    "Injuries": "0,000,0010",
    "Description": "17-year-old Wayne Phillips, was killed when he was caught between two youths who were fighting in the hallway of Armstrong High School.[159]",
    "coords": {
      "lat": 37.5407246,
      "lon": -77.4360481
    }
  },
  {
    "Date": "000000001973-11-06-0000November 6, 1973",
    "Location": "Oakland, California !Oakland, California",
    "Deaths": "0,000,0011",
    "Injuries": "0,000,0011",
    "Description": "School superintendent Marcus Foster, was killed and his assistant Robert Blackburn, was wounded when members of the Symbionese Liberation Army opened fire on them as they exited a school board meeting. Two members of the SLA were later arrested and convicted of the crime. Both were sentenced to life in prison without the possibility of parole. The SLA had reportedly believed that Foster supported a measure to install police on school grounds and make students carry identification cards. In reality, Foster opposed both measures.[160]",
    "coords": {
      "lat": 37.8043637,
      "lon": -122.2711137
    }
  },
  {
    "Date": "000000001974-01-17-0000January 17, 1974",
    "Location": "Chicago, Illinois !Chicago, Illinois",
    "Deaths": "0,000,0011",
    "Injuries": "0,000,0010",
    "Description": "52-year-old elementary school principal, Rudolph Jezek Jr., was killed in his office by 14-year-old Steven Guy, a former student said to be angry about being transferred to a social adjustment center.[161]",
    "coords": {
      "lat": 41.8781136,
      "lon": -87.6297982
    }
  },
  {
    "Date": "000000001974-03-22-0000March 22, 1974",
    "Location": "Brownstown, Indiana !Brownstown, Indiana",
    "Deaths": "0,000,0011",
    "Injuries": "0,000,0010",
    "Description": "48-year-old Jessie Blevins, athletic director at Brownstown Central High School, was fatally shot in the school parking lot by a 17-year-old student waiting for him. He gave the police no motive.[162]",
    "coords": {
      "lat": 38.87894259999999,
      "lon": -86.0419247
    }
  },
  {
    "Date": "000000001974-10-04-0000October 4, 1974",
    "Location": "Kent, Ohio !Kent, Ohio",
    "Deaths": "0,000,0010",
    "Injuries": "0,000,0011",
    "Description": "19-year-old McKeesport student, Ray D. Gilmore, was wounded in a scuffle with two men in his third floor campus dormitory room. 26-year-old Benjamin F. Goodman and 22-year-old Carl Bell, who were not students, had their .32 caliber pistols taken and were wrestled to the floor by other students.[163]",
    "coords": {
      "lat": 41.1536674,
      "lon": -81.3578859
    }
  },
  {
    "Date": "000000001974-12-30-0000December 30, 1974",
    "Location": "Olean, New York !Olean, New York",
    "Deaths": "0,000,0013",
    "Injuries": "0,000,00111",
    "Description": "During a two-and-a-half-hour siege, 18-year-old honor student, Anthony Barbaro, the best on his rifle team, killed three adults in and around his high school and wounded eleven other persons.[155][164] He shot from the windows out at the street and neighborhood. The school was closed for the Christmas holiday.[165]",
    "coords": {
      "lat": 42.083639,
      "lon": -78.42992699999999
    }
  },
  {
    "Date": "000000001975-02-24-0000February 24, 1975",
    "Location": "Penns Grove, New Jersey !Penns Grove, New Jersey",
    "Deaths": "0,000,0011",
    "Injuries": "0,000,0011",
    "Description": "24-year-old David Gary killed the 33-year-old Reverend Thomas Quinlan, inside a classroom at St. James School. Quinlan was the school's principal. A teacher was also wounded.[166]",
    "coords": {
      "lat": 39.7295581,
      "lon": -75.46797339999999
    }
  },
  {
    "Date": "000000001975-03-18-0000March 18, 1975",
    "Location": "St. Louis, Missouri !St. Louis, Missouri",
    "Deaths": "0,000,0011",
    "Injuries": "0,000,0010",
    "Description": "16-year-old Stephen Goods, a bystander, was killed during a fight between other teens. Three youths were convicted for the homicide.[164]",
    "coords": {
      "lat": 38.6270025,
      "lon": -90.19940419999999
    }
  },
  {
    "Date": "000000001975-09-11-0000September 11, 1975",
    "Location": "Oklahoma City, Oklahoma !Oklahoma City, Oklahoma",
    "Deaths": "0,000,0011",
    "Injuries": "0,000,0015",
    "Description": "Student James Briggs killed fellow student Randy Truitt at Grant High School, wounding several others.[167]",
    "coords": {
      "lat": 35.4675602,
      "lon": -97.5164276
    }
  },
  {
    "Date": "000000001976-02-12-0000February 12, 1976",
    "Location": "Detroit, Michigan !Detroit, Michigan",
    "Deaths": "0,000,0010",
    "Injuries": "0,000,0015",
    "Description": "Intruders entered Murray-Wright High School, shooting and wounding five students after an apparent dispute over a girlfriend of one of the intruders.[168]",
    "coords": {
      "lat": 42.331427,
      "lon": -83.0457538
    }
  },
  {
    "Date": "000000001976-07-12-0000July 12, 1976",
    "Location": "Fullerton, California !Fullerton, California",
    "Deaths": "0,000,0017",
    "Injuries": "0,000,0012",
    "Description": "The gunman, 37-year-old Edward Charles Allaway, was a custodian at the California State University, Fullerton library. Allaway killed seven people and wounded two others in the library's first-floor lobby and at the building's Instructional Media Center (IMC), located in the basement.",
    "coords": {
      "lat": 33.8703645,
      "lon": -117.9242123
    }
  },
  {
    "Date": "000000001976-11-10-0000November 10, 1976",
    "Location": "Detroit, Michigan !Detroit, Michigan",
    "Deaths": "0,000,0011",
    "Injuries": "0,000,0010",
    "Description": "46-year-old Al Lewis, killed his estranged wife, 46-year-old Betty McCaster, as she was teaching thirty-six 6-and-7-year-old students at Burt Elementary School.[169]",
    "coords": {
      "lat": 42.331427,
      "lon": -83.0457538
    }
  },
  {
    "Date": "000000001977-04-07-0000April 7, 1977",
    "Location": "Whitharral, Texas !Whitharral, Texas",
    "Deaths": "0,000,0011",
    "Injuries": "0,000,0010",
    "Description": "High School principal, M. O. Tripp, was killed on the front steps of the school by 17-year-old student, Ricardo Lopez, for unknown reasons.[170]",
    "coords": {
      "lat": 33.7378669,
      "lon": -102.3266173
    }
  },
  {
    "Date": "000000001978-01-11-0000January 11, 1978",
    "Location": "Hopkinsville, Kentucky !Hopkinsville, Kentucky",
    "Deaths": "0,000,0010",
    "Injuries": "0,000,0011",
    "Description": "At 8:10 a.m., 13-year-old student, Andre Davis, was wounded while watching a fight between two students in the front lobby of Christian County Middle School, one of whom had a gun. A 16-year-old was charged with the assault.[171]",
    "coords": {
      "lat": 36.8656008,
      "lon": -87.4886186
    }
  },
  {
    "Date": "000000001978-02-09-0000February 9, 1978",
    "Location": "St. Albans, West Virginia !St. Albans, West Virginia",
    "Deaths": "0,000,0011",
    "Injuries": "0,000,0010",
    "Description": "14-year-old Hayes Junior High School student, Stuart Wayne Perrock, killed 14-year-old schoolmate, Arthur Clinton Smith.[172]",
    "coords": {
      "lat": 38.3793695,
      "lon": -81.8191658
    }
  },
  {
    "Date": "000000001978-02-22-0000February 22, 1978",
    "Location": "Lansing, Michigan !Lansing, Michigan",
    "Deaths": "0,000,0011",
    "Injuries": "0,000,0011",
    "Description": "After being taunted for his beliefs, 15-year-old Roger Needham, self-proclaimed neo-Nazi, killed one student and wounded a second with a pistol at Everett High School.[164][173]",
    "coords": {
      "lat": 42.732535,
      "lon": -84.5555347
    }
  },
  {
    "Date": "000000001978-04-26-0000April 26, 1978",
    "Location": "Dallas, Texas !Dallas, Texas",
    "Deaths": "0,000,0011",
    "Injuries": "0,000,0010",
    "Description": "38-year-old Woodrow Porter, a janitor at Paul Dunbar Elementary School, was killed by the 56-year-old grandmother of an 8-year-old who was allegedly spanked by Porter earlier.[174]",
    "coords": {
      "lat": 32.7766642,
      "lon": -96.79698789999999
    }
  },
  {
    "Date": "000000001978-05-18-0000May 18, 1978",
    "Location": "Austin, Texas !Austin, Texas",
    "Deaths": "0,000,0011",
    "Injuries": "0,000,0010",
    "Description": "13-year-old John Daniel Christian, son of Lyndon B. Johnson's former press secretary George Christian, killed his English teacher, 29-year-old Wilbur Grayson, with his father's rifle in front of approximately thirty classmates at Murchison Junior High School.[155][164] Christian was arrested and charged but not prosecuted; he was committed to a mental hospital where he was treated for a period and released.[175]",
    "coords": {
      "lat": 30.267153,
      "lon": -97.7430608
    }
  },
  {
    "Date": "000000001978-10-17-0000October 17, 1978",
    "Location": "University City, Missouri !University City, Missouri",
    "Deaths": "0,000,0010",
    "Injuries": "0,000,0014",
    "Description": "18-year-old Larry Ward and two companions were escorted from the halls of University City High School following a fight with 18-year-old student, Carl Triplett. Ward ran back into the building with a gun and fired shots into a group, critically injuring Triplett in the chest and hip, and wounding 17-year-old Angela Darden and 16-year-old Jennifer Pride. Ward sustained a head injury as he was tackled by assistant principal, Franklin McCallie. His companions grabbed the gun and fled.[176]",
    "coords": {
      "lat": 38.6682407,
      "lon": -90.3324856
    }
  },
  {
    "Date": "000000001978-10-17-0000October 17, 1978",
    "Location": "Lanett, Alabama !Lanett, Alabama",
    "Deaths": "0,000,0010",
    "Injuries": "0,000,0011",
    "Description": "13-year-old Robin Robinson, was paddled by Lanett Junior High School principal, Lewis Hoggs, after having a disagreement with another student. Robinson left the school, and returned with a .22-caliber handgun and shot Hoggs, grazing the top of his head.[155][177][178] Robinson was arrested two hours later about two blocks from the school, and later charged in juvenile court.[175][179][180]",
    "coords": {
      "lat": 32.86873910000001,
      "lon": -85.1904971
    }
  },
  {
    "Date": "000000001979-01-29-0000January 29, 1979",
    "Location": "San Diego, California !San Diego, California",
    "Deaths": "0,000,0012",
    "Injuries": "0,000,0019",
    "Description": "Cleveland Elementary School shooting: 16-year-old Brenda Spencer opened fire on Grover Cleveland Elementary School from her home across the street, killing two adults and wounding nine people.[164][181][182][183][184][185]",
    "coords": {
      "lat": 32.715738,
      "lon": -117.1610838
    }
  },
  {
    "Date": "000000001979-04-16-0000April 16, 1979",
    "Location": "Milwaukee, Wisconsin !Milwaukee, Wisconsin",
    "Deaths": "0,000,0010",
    "Injuries": "0,000,0011",
    "Description": "17-year-old Timothy Stahle was critically wounded in the leg and upper thigh, with shot gun pellets, as he threw rocks at the windows of Wisconsin Lutheran High School. 28-year-old school janitor, Kenneth B. Stein, was arrested.[186]",
    "coords": {
      "lat": 43.0389025,
      "lon": -87.9064736
    }
  },
  {
    "Date": "000000001979-09-28-0000September 28, 1979",
    "Location": "Charlestown, Massachusetts !Charlestown, Massachusetts",
    "Deaths": "0,000,0010",
    "Injuries": "0,000,0011",
    "Description": "15-year-old sophomore, Darryl Williams, was shot in the neck by a sniper during the half-time interval, while standing with teammates and coach in the end zone of the Charlestown High School football field. The player for the predominantly black Jamaica Plain High School team was left paralysed. A racial motivation was determined by Mayor Kevin White.[187] 17-year-old white youths, Joseph Nardone and Stephen McGonagle, were charged with the shooting and received ten year sentences.[188]",
    "coords": {
      "lat": 42.3782065,
      "lon": -71.0602131
    }
  }
]